src/analytic_properties_pkg/__init__.py
src/analytic_properties_pkg/analytic_properties.py
example_package_analytic_lib-0.0.1.dist-info/METADATA
example_package_analytic_lib-0.0.1.dist-info/WHEEL
example_package_analytic_lib-0.0.1.dist-info/licenses/LICENSE
example_package_analytic_lib-0.0.1.dist-info/RECORD
