Metadata-Version: 2.1
Name: example_package_analytic_lib
Version: 0.0.1
Summary: A small package that calculates Average and percentages
Project-URL: Homepage, https://github.com/pypa/sampleproject
Project-URL: Bug Tracker, https://github.com/pypa/sampleproject/issues
Author-email: Franklin <onyiafranklin89@gmail.com>
License-File: LICENSE
Classifier: License :: OSI Approved :: MIT License
Classifier: Operating System :: OS Independent
Classifier: Programming Language :: Python :: 3
Requires-Python: >=3.7
